MANIFEST.in
README.md
setup.py
cmtestrunner/__init__.py
cmtestrunner/case_insensitive_dict.py
cmtestrunner/json_traverser.py
cmtestrunner/middleware.py
cmtestrunner/object_manager.py
cmtestrunner/processor.py
cmtestrunner/test.py
cmtestrunner/test_runner.py
cmtestrunner/verify_enigne.py
cmtestrunner.egg-info/PKG-INFO
cmtestrunner.egg-info/SOURCES.txt
cmtestrunner.egg-info/dependency_links.txt
cmtestrunner.egg-info/not-zip-safe
cmtestrunner.egg-info/requires.txt
cmtestrunner.egg-info/top_level.txt
cmtestrunner/management/__init__.py
cmtestrunner/management/commands/__init__.py
cmtestrunner/management/commands/createtest.py
cmtestrunner/management/commands/createtestpool.py
cmtestrunner/management/commands/createunittest.py
cmtestrunner/management/commands/iwanttotest.py
cmtestrunner/management/templates/endpoints_template.txt
cmtestrunner/management/templates/test_methods_template.txt
cmtestrunner/management/templates/test_runner_template.txt
cmtestrunner/management/templates/tests_template.txt
cmtestrunner/management/templates/unit_test_import_template.txt
cmtestrunner/management/templates/unit_test_method_template.txt
cmtestrunner/templates/exceptions.html
cmtestrunner/templates/modal.html
cmtestrunner/templates/report.html
cmtestrunner/templates/test_details.html
cmtestrunner/templates/test_pool.html