Metadata-Version: 2.1
Name: cmtestrunner
Version: 2.2.10
Summary: custom test runner for API test
Home-page: https://github.com/tasin-megamind/cmtestrunner
Author: Tasin Nawaz
Author-email: tasin.buet@gmail.com
License: CM
Platform: UNKNOWN
